<?xml version="1.0" encoding="UTF-8"?>
<monster name="Kratos" nameDescription="a kratos" race="blood" experience="5000" speed="350" manacost="0">

*******************************************************************************************
*                         KRATOS: This monster Was made by Amy Azzkaban                   *
*                                  CRAZY CREATIONS PACK VOL.2.                            *
*                                EXCLUSIVO PARA BLACKTIBIA.ORG                            *
*******************************************************************************************

<health now="8000" max="8000"/>
<look type="367" head="91" body="38" legs="114" feet="94" addons="0" corpse="6080"/>
<targetchange interval="5000" chance="30"/>
<strategy attack="100" defense="0"/>
     <flags>
           <flag summonable="0"/>
           <flag attackable="1"/>
           <flag hostile="1"/>
           <flag illusionable="0"/>
           <flag convinceable="0"/>
           <flag pushable="0"/>
           <flag canpushitems="1"/>
           <flag canpushcreatures="1"/>
           <flag targetdistance="1"/>
           <flag staticattack="70"/>
           <flag runonhealth="0"/>
     </flags>
     <attacks>
              <attack name="melee" interval="2000" skill="90" attack="90"/>               
	      <attack name="physical" interval="2000" chance="90" range="7" min="-40" max="-390">
	      <attribute key="shootEffect" value="holy"/>
	      <attribute key="areaEffect" value="holydamage"/>
     </attack>
	      <attack name="skills" interval="2000" chance="22" target="0" radius="4" shielding="-20">
	      <attribute key="areaEffect" value="holydamage"/>
     </attack>
              <attack name="speed" interval="4000" chance="27" radius="4" range="6" target="1" speedchange="-1900" duration="1500">
	      <attribute key="areaEffect" value="redfirework"/>
              <attribute key="shootEffect" value="whirlwindsword"/>
     </attack>
     </attacks>
              <defenses armor="50" defense="50">
              <defense name="healing" interval="2000" chance="20" min="90" max="250">
              <attribute key="areaEffect" value="holyarea"/>
     </defense>
	      <defense name="speed" interval="6000" chance="40" speedchange="10000" duration="200">
	      <attribute key="areaEffect" value="groundshaker"/>
     </defense>
     </defenses>
     <elements>
              <element firePercent="-30"/>
              <element energyPercent="-20"/>
              <element icePercent="-20"/>
              <element holyPercent="60"/>
     </elements>
     <immunities>
                <immunity outfit="1"/>
                <immunity drunk="0"/>
                <immunity invisible="1"/>
     </immunities>
     <voices interval="5000" chance="24">
                <voice sentence="Humm." yell="1"/>
                <voice sentence="DIE STUPID MORTAL." yell="1"/>
        </voices>
        <loot>
        </loot>
</monster>